[{"actor":{"login":"kennylevinsen","id":176245,"node_id":"MDQ6VXNlcjE3NjI0NQ==","avatar_url":"https://avatars.githubusercontent.com/u/176245?v=4","gravatar_id":"","url":"https://api.github.com/users/kennylevinsen","html_url":"https://github.com/kennylevinsen","followers_url":"https://api.github.com/users/kennylevinsen/followers","following_url":"https://api.github.com/users/kennylevinsen/following{/other_user}","gists_url":"https://api.github.com/users/kennylevinsen/gists{/gist_id}","starred_url":"https://api.github.com/users/kennylevinsen/starred{/owner}{/repo}","subscriptions_url":"https://api.github.com/users/kennylevinsen/subscriptions","organizations_url":"https://api.github.com/users/kennylevinsen/orgs","repos_url":"https://api.github.com/users/kennylevinsen/repos","events_url":"https://api.github.com/users/kennylevinsen/events{/privacy}","received_events_url":"https://api.github.com/users/kennylevinsen/received_events","type":"User","user_view_type":"public","site_admin":false},"created_at":"2019-10-24T11:56:34Z","updated_at":"2019-10-24T11:56:34Z","source":{"type":"issue","issue":{"url":"https://api.github.com/repos/alacritty/alacritty/issues/2911","repository_url":"https://api.github.com/repos/alacritty/alacritty","labels_url":"https://api.github.com/repos/alacritty/alacritty/issues/2911/labels{/name}","comments_url":"https://api.github.com/repos/alacritty/alacritty/issues/2911/comments","events_url":"https://api.github.com/repos/alacritty/alacritty/issues/2911/events","html_url":"https://github.com/alacritty/alacritty/issues/2911","id":511609148,"node_id":"MDU6SXNzdWU1MTE2MDkxNDg=","number":2911,"title":"Background is semi opaque during visual bell animation","user":{"login":"kchibisov","id":27620401,"node_id":"MDQ6VXNlcjI3NjIwNDAx","avatar_url":"https://avatars.githubusercontent.com/u/27620401?v=4","gravatar_id":"","url":"https://api.github.com/users/kchibisov","html_url":"https://github.com/kchibisov","followers_url":"https://api.github.com/users/kchibisov/followers","following_url":"https://api.github.com/users/kchibisov/following{/other_user}","gists_url":"https://api.github.com/users/kchibisov/gists{/gist_id}","starred_url":"https://api.github.com/users/kchibisov/starred{/owner}{/repo}","subscriptions_url":"https://api.github.com/users/kchibisov/subscriptions","organizations_url":"https://api.github.com/users/kchibisov/orgs","repos_url":"https://api.github.com/users/kchibisov/repos","events_url":"https://api.github.com/users/kchibisov/events{/privacy}","received_events_url":"https://api.github.com/users/kchibisov/received_events","type":"User","user_view_type":"public","site_admin":false},"labels":[{"id":327960155,"node_id":"MDU6TGFiZWwzMjc5NjAxNTU=","url":"https://api.github.com/repos/alacritty/alacritty/labels/B%20-%20bug","name":"B - bug","color":"c6071e","default":false,"description":""}],"state":"closed","locked":false,"assignee":null,"assignees":[],"milestone":null,"comments":5,"created_at":"2019-10-23T22:42:05Z","updated_at":"2019-10-26T19:45:50Z","closed_at":"2019-10-26T19:45:50Z","author_association":"MEMBER","type":null,"active_lock_reason":null,"sub_issues_summary":{"total":0,"completed":0,"percent_completed":0},"issue_dependencies_summary":{"blocked_by":0,"total_blocked_by":0,"blocking":0,"total_blocking":0},"repository":{"id":51980455,"node_id":"MDEwOlJlcG9zaXRvcnk1MTk4MDQ1NQ==","name":"alacritty","full_name":"alacritty/alacritty","private":false,"owner":{"login":"alacritty","id":29714349,"node_id":"MDEyOk9yZ2FuaXphdGlvbjI5NzE0MzQ5","avatar_url":"https://avatars.githubusercontent.com/u/29714349?v=4","gravatar_id":"","url":"https://api.github.com/users/alacritty","html_url":"https://github.com/alacritty","followers_url":"https://api.github.com/users/alacritty/followers","following_url":"https://api.github.com/users/alacritty/following{/other_user}","gists_url":"https://api.github.com/users/alacritty/gists{/gist_id}","starred_url":"https://api.github.com/users/alacritty/starred{/owner}{/repo}","subscriptions_url":"https://api.github.com/users/alacritty/subscriptions","organizations_url":"https://api.github.com/users/alacritty/orgs","repos_url":"https://api.github.com/users/alacritty/repos","events_url":"https://api.github.com/users/alacritty/events{/privacy}","received_events_url":"https://api.github.com/users/alacritty/received_events","type":"Organization","user_view_type":"public","site_admin":false},"html_url":"https://github.com/alacritty/alacritty","description":"A cross-platform, OpenGL terminal emulator.","fork":false,"url":"https://api.github.com/repos/alacritty/alacritty","forks_url":"https://api.github.com/repos/alacritty/alacritty/forks","keys_url":"https://api.github.com/repos/alacritty/alacritty/keys{/key_id}","collaborators_url":"https://api.github.com/repos/alacritty/alacritty/collaborators{/collaborator}","teams_url":"https://api.github.com/repos/alacritty/alacritty/teams","hooks_url":"https://api.github.com/repos/alacritty/alacritty/hooks","issue_events_url":"https://api.github.com/repos/alacritty/alacritty/issues/events{/number}","events_url":"https://api.github.com/repos/alacritty/alacritty/events","assignees_url":"https://api.github.com/repos/alacritty/alacritty/assignees{/user}","branches_url":"https://api.github.com/repos/alacritty/alacritty/branches{/branch}","tags_url":"https://api.github.com/repos/alacritty/alacritty/tags","blobs_url":"https://api.github.com/repos/alacritty/alacritty/git/blobs{/sha}","git_tags_url":"https://api.github.com/repos/alacritty/alacritty/git/tags{/sha}","git_refs_url":"https://api.github.com/repos/alacritty/alacritty/git/refs{/sha}","trees_url":"https://api.github.com/repos/alacritty/alacritty/git/trees{/sha}","statuses_url":"https://api.github.com/repos/alacritty/alacritty/statuses/{sha}","languages_url":"https://api.github.com/repos/alacritty/alacritty/languages","stargazers_url":"https://api.github.com/repos/alacritty/alacritty/stargazers","contributors_url":"https://api.github.com/repos/alacritty/alacritty/contributors","subscribers_url":"https://api.github.com/repos/alacritty/alacritty/subscribers","subscription_url":"https://api.github.com/repos/alacritty/alacritty/subscription","commits_url":"https://api.github.com/repos/alacritty/alacritty/commits{/sha}","git_commits_url":"https://api.github.com/repos/alacritty/alacritty/git/commits{/sha}","comments_url":"https://api.github.com/repos/alacritty/alacritty/comments{/number}","issue_comment_url":"https://api.github.com/repos/alacritty/alacritty/issues/comments{/number}","contents_url":"https://api.github.com/repos/alacritty/alacritty/contents/{+path}","compare_url":"https://api.github.com/repos/alacritty/alacritty/compare/{base}...{head}","merges_url":"https://api.github.com/repos/alacritty/alacritty/merges","archive_url":"https://api.github.com/repos/alacritty/alacritty/{archive_format}{/ref}","downloads_url":"https://api.github.com/repos/alacritty/alacritty/downloads","issues_url":"https://api.github.com/repos/alacritty/alacritty/issues{/number}","pulls_url":"https://api.github.com/repos/alacritty/alacritty/pulls{/number}","milestones_url":"https://api.github.com/repos/alacritty/alacritty/milestones{/number}","notifications_url":"https://api.github.com/repos/alacritty/alacritty/notifications{?since,all,participating}","labels_url":"https://api.github.com/repos/alacritty/alacritty/labels{/name}","releases_url":"https://api.github.com/repos/alacritty/alacritty/releases{/id}","deployments_url":"https://api.github.com/repos/alacritty/alacritty/deployments","created_at":"2016-02-18T05:02:30Z","updated_at":"2025-12-12T22:18:57Z","pushed_at":"2025-12-05T15:27:56Z","git_url":"git://github.com/alacritty/alacritty.git","ssh_url":"git@github.com:alacritty/alacritty.git","clone_url":"https://github.com/alacritty/alacritty.git","svn_url":"https://github.com/alacritty/alacritty","homepage":"https://alacritty.org","size":14099,"stargazers_count":61387,"watchers_count":61387,"language":"Rust","has_issues":true,"has_projects":false,"has_downloads":true,"has_wiki":true,"has_pages":false,"has_discussions":false,"forks_count":3243,"mirror_url":null,"archived":false,"disabled":false,"open_issues_count":331,"license":{"key":"apache-2.0","name":"Apache License 2.0","spdx_id":"Apache-2.0","url":"https://api.github.com/licenses/apache-2.0","node_id":"MDc6TGljZW5zZTI="},"allow_forking":true,"is_template":false,"web_commit_signoff_required":false,"topics":["bsd","gpu","linux","macos","opengl","rust","terminal","terminal-emulators","vte","windows"],"visibility":"public","forks":3243,"open_issues":331,"watchers":61387,"default_branch":"master","permissions":{"admin":false,"maintain":false,"push":false,"triage":false,"pull":true}},"body":"Arch Linux, Wayland(sway) and X11 (i3 + compton)\r\n\r\nDuring visual bell animation background is transparent(not fully though) with disabled transparency.\r\n\r\nEdit:\r\nWas able to repro on v0.3.3, so probably an old bug.","reactions":{"url":"https://api.github.com/repos/alacritty/alacritty/issues/2911/reactions","total_count":0,"+1":0,"-1":0,"laugh":0,"hooray":0,"confused":0,"heart":0,"rocket":0,"eyes":0},"timeline_url":"https://api.github.com/repos/alacritty/alacritty/issues/2911/timeline","performed_via_github_app":null,"state_reason":"completed"}},"event":"cross-referenced"},{"id":2740479782,"node_id":"MDE1OlJlZmVyZW5jZWRFdmVudDI3NDA0Nzk3ODI=","url":"https://api.github.com/repos/alacritty/alacritty/issues/events/2740479782","actor":{"login":"kennylevinsen","id":176245,"node_id":"MDQ6VXNlcjE3NjI0NQ==","avatar_url":"https://avatars.githubusercontent.com/u/176245?v=4","gravatar_id":"","url":"https://api.github.com/users/kennylevinsen","html_url":"https://github.com/kennylevinsen","followers_url":"https://api.github.com/users/kennylevinsen/followers","following_url":"https://api.github.com/users/kennylevinsen/following{/other_user}","gists_url":"https://api.github.com/users/kennylevinsen/gists{/gist_id}","starred_url":"https://api.github.com/users/kennylevinsen/starred{/owner}{/repo}","subscriptions_url":"https://api.github.com/users/kennylevinsen/subscriptions","organizations_url":"https://api.github.com/users/kennylevinsen/orgs","repos_url":"https://api.github.com/users/kennylevinsen/repos","events_url":"https://api.github.com/users/kennylevinsen/events{/privacy}","received_events_url":"https://api.github.com/users/kennylevinsen/received_events","type":"User","user_view_type":"public","site_admin":false},"event":"referenced","commit_id":"2761aeb6b0f71d7d8397e7f225d734b29d3960b5","commit_url":"https://api.github.com/repos/kennylevinsen/alacritty/commits/2761aeb6b0f71d7d8397e7f225d734b29d3960b5","created_at":"2019-10-24T12:00:52Z","performed_via_github_app":null},{"actor":{"login":"kennylevinsen","id":176245,"node_id":"MDQ6VXNlcjE3NjI0NQ==","avatar_url":"https://avatars.githubusercontent.com/u/176245?v=4","gravatar_id":"","url":"https://api.github.com/users/kennylevinsen","html_url":"https://github.com/kennylevinsen","followers_url":"https://api.github.com/users/kennylevinsen/followers","following_url":"https://api.github.com/users/kennylevinsen/following{/other_user}","gists_url":"https://api.github.com/users/kennylevinsen/gists{/gist_id}","starred_url":"https://api.github.com/users/kennylevinsen/starred{/owner}{/repo}","subscriptions_url":"https://api.github.com/users/kennylevinsen/subscriptions","organizations_url":"https://api.github.com/users/kennylevinsen/orgs","repos_url":"https://api.github.com/users/kennylevinsen/repos","events_url":"https://api.github.com/users/kennylevinsen/events{/privacy}","received_events_url":"https://api.github.com/users/kennylevinsen/received_events","type":"User","user_view_type":"public","site_admin":false},"created_at":"2019-10-24T12:01:22Z","updated_at":"2019-10-24T12:01:22Z","source":{"type":"issue","issue":{"url":"https://api.github.com/repos/alacritty/alacritty/issues/2915","repository_url":"https://api.github.com/repos/alacritty/alacritty","labels_url":"https://api.github.com/repos/alacritty/alacritty/issues/2915/labels{/name}","comments_url":"https://api.github.com/repos/alacritty/alacritty/issues/2915/comments","events_url":"https://api.github.com/repos/alacritty/alacritty/issues/2915/events","html_url":"https://github.com/alacritty/alacritty/pull/2915","id":511898396,"node_id":"MDExOlB1bGxSZXF1ZXN0MzMyMDEwMTMy","number":2915,"title":"Draw dirty terminal even when event queue is empty","user":{"login":"kennylevinsen","id":176245,"node_id":"MDQ6VXNlcjE3NjI0NQ==","avatar_url":"https://avatars.githubusercontent.com/u/176245?v=4","gravatar_id":"","url":"https://api.github.com/users/kennylevinsen","html_url":"https://github.com/kennylevinsen","followers_url":"https://api.github.com/users/kennylevinsen/followers","following_url":"https://api.github.com/users/kennylevinsen/following{/other_user}","gists_url":"https://api.github.com/users/kennylevinsen/gists{/gist_id}","starred_url":"https://api.github.com/users/kennylevinsen/starred{/owner}{/repo}","subscriptions_url":"https://api.github.com/users/kennylevinsen/subscriptions","organizations_url":"https://api.github.com/users/kennylevinsen/orgs","repos_url":"https://api.github.com/users/kennylevinsen/repos","events_url":"https://api.github.com/users/kennylevinsen/events{/privacy}","received_events_url":"https://api.github.com/users/kennylevinsen/received_events","type":"User","user_view_type":"public","site_admin":false},"labels":[],"state":"closed","locked":false,"assignee":null,"assignees":[],"milestone":null,"comments":3,"created_at":"2019-10-24T12:01:22Z","updated_at":"2019-10-24T22:42:12Z","closed_at":"2019-10-24T22:26:34Z","author_association":"CONTRIBUTOR","type":null,"active_lock_reason":null,"draft":false,"repository":{"id":51980455,"node_id":"MDEwOlJlcG9zaXRvcnk1MTk4MDQ1NQ==","name":"alacritty","full_name":"alacritty/alacritty","private":false,"owner":{"login":"alacritty","id":29714349,"node_id":"MDEyOk9yZ2FuaXphdGlvbjI5NzE0MzQ5","avatar_url":"https://avatars.githubusercontent.com/u/29714349?v=4","gravatar_id":"","url":"https://api.github.com/users/alacritty","html_url":"https://github.com/alacritty","followers_url":"https://api.github.com/users/alacritty/followers","following_url":"https://api.github.com/users/alacritty/following{/other_user}","gists_url":"https://api.github.com/users/alacritty/gists{/gist_id}","starred_url":"https://api.github.com/users/alacritty/starred{/owner}{/repo}","subscriptions_url":"https://api.github.com/users/alacritty/subscriptions","organizations_url":"https://api.github.com/users/alacritty/orgs","repos_url":"https://api.github.com/users/alacritty/repos","events_url":"https://api.github.com/users/alacritty/events{/privacy}","received_events_url":"https://api.github.com/users/alacritty/received_events","type":"Organization","user_view_type":"public","site_admin":false},"html_url":"https://github.com/alacritty/alacritty","description":"A cross-platform, OpenGL terminal emulator.","fork":false,"url":"https://api.github.com/repos/alacritty/alacritty","forks_url":"https://api.github.com/repos/alacritty/alacritty/forks","keys_url":"https://api.github.com/repos/alacritty/alacritty/keys{/key_id}","collaborators_url":"https://api.github.com/repos/alacritty/alacritty/collaborators{/collaborator}","teams_url":"https://api.github.com/repos/alacritty/alacritty/teams","hooks_url":"https://api.github.com/repos/alacritty/alacritty/hooks","issue_events_url":"https://api.github.com/repos/alacritty/alacritty/issues/events{/number}","events_url":"https://api.github.com/repos/alacritty/alacritty/events","assignees_url":"https://api.github.com/repos/alacritty/alacritty/assignees{/user}","branches_url":"https://api.github.com/repos/alacritty/alacritty/branches{/branch}","tags_url":"https://api.github.com/repos/alacritty/alacritty/tags","blobs_url":"https://api.github.com/repos/alacritty/alacritty/git/blobs{/sha}","git_tags_url":"https://api.github.com/repos/alacritty/alacritty/git/tags{/sha}","git_refs_url":"https://api.github.com/repos/alacritty/alacritty/git/refs{/sha}","trees_url":"https://api.github.com/repos/alacritty/alacritty/git/trees{/sha}","statuses_url":"https://api.github.com/repos/alacritty/alacritty/statuses/{sha}","languages_url":"https://api.github.com/repos/alacritty/alacritty/languages","stargazers_url":"https://api.github.com/repos/alacritty/alacritty/stargazers","contributors_url":"https://api.github.com/repos/alacritty/alacritty/contributors","subscribers_url":"https://api.github.com/repos/alacritty/alacritty/subscribers","subscription_url":"https://api.github.com/repos/alacritty/alacritty/subscription","commits_url":"https://api.github.com/repos/alacritty/alacritty/commits{/sha}","git_commits_url":"https://api.github.com/repos/alacritty/alacritty/git/commits{/sha}","comments_url":"https://api.github.com/repos/alacritty/alacritty/comments{/number}","issue_comment_url":"https://api.github.com/repos/alacritty/alacritty/issues/comments{/number}","contents_url":"https://api.github.com/repos/alacritty/alacritty/contents/{+path}","compare_url":"https://api.github.com/repos/alacritty/alacritty/compare/{base}...{head}","merges_url":"https://api.github.com/repos/alacritty/alacritty/merges","archive_url":"https://api.github.com/repos/alacritty/alacritty/{archive_format}{/ref}","downloads_url":"https://api.github.com/repos/alacritty/alacritty/downloads","issues_url":"https://api.github.com/repos/alacritty/alacritty/issues{/number}","pulls_url":"https://api.github.com/repos/alacritty/alacritty/pulls{/number}","milestones_url":"https://api.github.com/repos/alacritty/alacritty/milestones{/number}","notifications_url":"https://api.github.com/repos/alacritty/alacritty/notifications{?since,all,participating}","labels_url":"https://api.github.com/repos/alacritty/alacritty/labels{/name}","releases_url":"https://api.github.com/repos/alacritty/alacritty/releases{/id}","deployments_url":"https://api.github.com/repos/alacritty/alacritty/deployments","created_at":"2016-02-18T05:02:30Z","updated_at":"2025-12-12T22:18:57Z","pushed_at":"2025-12-05T15:27:56Z","git_url":"git://github.com/alacritty/alacritty.git","ssh_url":"git@github.com:alacritty/alacritty.git","clone_url":"https://github.com/alacritty/alacritty.git","svn_url":"https://github.com/alacritty/alacritty","homepage":"https://alacritty.org","size":14099,"stargazers_count":61387,"watchers_count":61387,"language":"Rust","has_issues":true,"has_projects":false,"has_downloads":true,"has_wiki":true,"has_pages":false,"has_discussions":false,"forks_count":3243,"mirror_url":null,"archived":false,"disabled":false,"open_issues_count":331,"license":{"key":"apache-2.0","name":"Apache License 2.0","spdx_id":"Apache-2.0","url":"https://api.github.com/licenses/apache-2.0","node_id":"MDc6TGljZW5zZTI="},"allow_forking":true,"is_template":false,"web_commit_signoff_required":false,"topics":["bsd","gpu","linux","macos","opengl","rust","terminal","terminal-emulators","vte","windows"],"visibility":"public","forks":3243,"open_issues":331,"watchers":61387,"default_branch":"master","permissions":{"admin":false,"maintain":false,"push":false,"triage":false,"pull":true}},"pull_request":{"url":"https://api.github.com/repos/alacritty/alacritty/pulls/2915","html_url":"https://github.com/alacritty/alacritty/pull/2915","diff_url":"https://github.com/alacritty/alacritty/pull/2915.diff","patch_url":"https://github.com/alacritty/alacritty/pull/2915.patch","merged_at":"2019-10-24T22:26:34Z"},"body":"If the event queue was empty, we would stop the event loop even if the terminal was dirty. This lead to the terminal not being drawn when running animations unless something else was causing events to queue, such as user input.\r\n\r\nThis change ensures that the terminal is always drawn on EventsCleared when dirty.\r\n\r\nFixes #2914.","reactions":{"url":"https://api.github.com/repos/alacritty/alacritty/issues/2915/reactions","total_count":0,"+1":0,"-1":0,"laugh":0,"hooray":0,"confused":0,"heart":0,"rocket":0,"eyes":0},"timeline_url":"https://api.github.com/repos/alacritty/alacritty/issues/2915/timeline","performed_via_github_app":null,"state_reason":null}},"event":"cross-referenced"},{"id":2741213055,"node_id":"MDEyOkxhYmVsZWRFdmVudDI3NDEyMTMwNTU=","url":"https://api.github.com/repos/alacritty/alacritty/issues/events/2741213055","actor":{"login":"chrisduerr","id":8886672,"node_id":"MDQ6VXNlcjg4ODY2NzI=","avatar_url":"https://avatars.githubusercontent.com/u/8886672?v=4","gravatar_id":"","url":"https://api.github.com/users/chrisduerr","html_url":"https://github.com/chrisduerr","followers_url":"https://api.github.com/users/chrisduerr/followers","following_url":"https://api.github.com/users/chrisduerr/following{/other_user}","gists_url":"https://api.github.com/users/chrisduerr/gists{/gist_id}","starred_url":"https://api.github.com/users/chrisduerr/starred{/owner}{/repo}","subscriptions_url":"https://api.github.com/users/chrisduerr/subscriptions","organizations_url":"https://api.github.com/users/chrisduerr/orgs","repos_url":"https://api.github.com/users/chrisduerr/repos","events_url":"https://api.github.com/users/chrisduerr/events{/privacy}","received_events_url":"https://api.github.com/users/chrisduerr/received_events","type":"User","user_view_type":"public","site_admin":false},"event":"labeled","commit_id":null,"commit_url":null,"created_at":"2019-10-24T15:24:40Z","label":{"name":"B - bug","color":"c6071e"},"performed_via_github_app":null},{"id":2741213417,"node_id":"MDE3OlJlbmFtZWRUaXRsZUV2ZW50Mjc0MTIxMzQxNw==","url":"https://api.github.com/repos/alacritty/alacritty/issues/events/2741213417","actor":{"login":"chrisduerr","id":8886672,"node_id":"MDQ6VXNlcjg4ODY2NzI=","avatar_url":"https://avatars.githubusercontent.com/u/8886672?v=4","gravatar_id":"","url":"https://api.github.com/users/chrisduerr","html_url":"https://github.com/chrisduerr","followers_url":"https://api.github.com/users/chrisduerr/followers","following_url":"https://api.github.com/users/chrisduerr/following{/other_user}","gists_url":"https://api.github.com/users/chrisduerr/gists{/gist_id}","starred_url":"https://api.github.com/users/chrisduerr/starred{/owner}{/repo}","subscriptions_url":"https://api.github.com/users/chrisduerr/subscriptions","organizations_url":"https://api.github.com/users/chrisduerr/orgs","repos_url":"https://api.github.com/users/chrisduerr/repos","events_url":"https://api.github.com/users/chrisduerr/events{/privacy}","received_events_url":"https://api.github.com/users/chrisduerr/received_events","type":"User","user_view_type":"public","site_admin":false},"event":"renamed","commit_id":null,"commit_url":null,"created_at":"2019-10-24T15:24:47Z","rename":{"from":"[wayland] Visual bell animation stalls","to":"Visual bell animation stalls"},"performed_via_github_app":null},{"id":2741213990,"node_id":"MDEyOkxhYmVsZWRFdmVudDI3NDEyMTM5OTA=","url":"https://api.github.com/repos/alacritty/alacritty/issues/events/2741213990","actor":{"login":"chrisduerr","id":8886672,"node_id":"MDQ6VXNlcjg4ODY2NzI=","avatar_url":"https://avatars.githubusercontent.com/u/8886672?v=4","gravatar_id":"","url":"https://api.github.com/users/chrisduerr","html_url":"https://github.com/chrisduerr","followers_url":"https://api.github.com/users/chrisduerr/followers","following_url":"https://api.github.com/users/chrisduerr/following{/other_user}","gists_url":"https://api.github.com/users/chrisduerr/gists{/gist_id}","starred_url":"https://api.github.com/users/chrisduerr/starred{/owner}{/repo}","subscriptions_url":"https://api.github.com/users/chrisduerr/subscriptions","organizations_url":"https://api.github.com/users/chrisduerr/orgs","repos_url":"https://api.github.com/users/chrisduerr/repos","events_url":"https://api.github.com/users/chrisduerr/events{/privacy}","received_events_url":"https://api.github.com/users/chrisduerr/received_events","type":"User","user_view_type":"public","site_admin":false},"event":"labeled","commit_id":null,"commit_url":null,"created_at":"2019-10-24T15:24:56Z","label":{"name":"S - render","color":"5319e7"},"performed_via_github_app":null},{"id":2741214248,"node_id":"MDEyOkxhYmVsZWRFdmVudDI3NDEyMTQyNDg=","url":"https://api.github.com/repos/alacritty/alacritty/issues/events/2741214248","actor":{"login":"chrisduerr","id":8886672,"node_id":"MDQ6VXNlcjg4ODY2NzI=","avatar_url":"https://avatars.githubusercontent.com/u/8886672?v=4","gravatar_id":"","url":"https://api.github.com/users/chrisduerr","html_url":"https://github.com/chrisduerr","followers_url":"https://api.github.com/users/chrisduerr/followers","following_url":"https://api.github.com/users/chrisduerr/following{/other_user}","gists_url":"https://api.github.com/users/chrisduerr/gists{/gist_id}","starred_url":"https://api.github.com/users/chrisduerr/starred{/owner}{/repo}","subscriptions_url":"https://api.github.com/users/chrisduerr/subscriptions","organizations_url":"https://api.github.com/users/chrisduerr/orgs","repos_url":"https://api.github.com/users/chrisduerr/repos","events_url":"https://api.github.com/users/chrisduerr/events{/privacy}","received_events_url":"https://api.github.com/users/chrisduerr/received_events","type":"User","user_view_type":"public","site_admin":false},"event":"labeled","commit_id":null,"commit_url":null,"created_at":"2019-10-24T15:25:01Z","label":{"name":"B - regression","color":"c6071e"},"performed_via_github_app":null},{"id":2741214666,"node_id":"MDE1Ok1pbGVzdG9uZWRFdmVudDI3NDEyMTQ2NjY=","url":"https://api.github.com/repos/alacritty/alacritty/issues/events/2741214666","actor":{"login":"chrisduerr","id":8886672,"node_id":"MDQ6VXNlcjg4ODY2NzI=","avatar_url":"https://avatars.githubusercontent.com/u/8886672?v=4","gravatar_id":"","url":"https://api.github.com/users/chrisduerr","html_url":"https://github.com/chrisduerr","followers_url":"https://api.github.com/users/chrisduerr/followers","following_url":"https://api.github.com/users/chrisduerr/following{/other_user}","gists_url":"https://api.github.com/users/chrisduerr/gists{/gist_id}","starred_url":"https://api.github.com/users/chrisduerr/starred{/owner}{/repo}","subscriptions_url":"https://api.github.com/users/chrisduerr/subscriptions","organizations_url":"https://api.github.com/users/chrisduerr/orgs","repos_url":"https://api.github.com/users/chrisduerr/repos","events_url":"https://api.github.com/users/chrisduerr/events{/privacy}","received_events_url":"https://api.github.com/users/chrisduerr/received_events","type":"User","user_view_type":"public","site_admin":false},"event":"milestoned","commit_id":null,"commit_url":null,"created_at":"2019-10-24T15:25:09Z","milestone":{"title":"Version 0.3.4"},"performed_via_github_app":null},{"id":2742404067,"node_id":"MDExOkNsb3NlZEV2ZW50Mjc0MjQwNDA2Nw==","url":"https://api.github.com/repos/alacritty/alacritty/issues/events/2742404067","actor":{"login":"chrisduerr","id":8886672,"node_id":"MDQ6VXNlcjg4ODY2NzI=","avatar_url":"https://avatars.githubusercontent.com/u/8886672?v=4","gravatar_id":"","url":"https://api.github.com/users/chrisduerr","html_url":"https://github.com/chrisduerr","followers_url":"https://api.github.com/users/chrisduerr/followers","following_url":"https://api.github.com/users/chrisduerr/following{/other_user}","gists_url":"https://api.github.com/users/chrisduerr/gists{/gist_id}","starred_url":"https://api.github.com/users/chrisduerr/starred{/owner}{/repo}","subscriptions_url":"https://api.github.com/users/chrisduerr/subscriptions","organizations_url":"https://api.github.com/users/chrisduerr/orgs","repos_url":"https://api.github.com/users/chrisduerr/repos","events_url":"https://api.github.com/users/chrisduerr/events{/privacy}","received_events_url":"https://api.github.com/users/chrisduerr/received_events","type":"User","user_view_type":"public","site_admin":false},"event":"closed","commit_id":null,"commit_url":null,"created_at":"2019-10-24T22:26:34Z","state_reason":null,"performed_via_github_app":null},{"id":2742404110,"node_id":"MDE1OlJlZmVyZW5jZWRFdmVudDI3NDI0MDQxMTA=","url":"https://api.github.com/repos/alacritty/alacritty/issues/events/2742404110","actor":{"login":"chrisduerr","id":8886672,"node_id":"MDQ6VXNlcjg4ODY2NzI=","avatar_url":"https://avatars.githubusercontent.com/u/8886672?v=4","gravatar_id":"","url":"https://api.github.com/users/chrisduerr","html_url":"https://github.com/chrisduerr","followers_url":"https://api.github.com/users/chrisduerr/followers","following_url":"https://api.github.com/users/chrisduerr/following{/other_user}","gists_url":"https://api.github.com/users/chrisduerr/gists{/gist_id}","starred_url":"https://api.github.com/users/chrisduerr/starred{/owner}{/repo}","subscriptions_url":"https://api.github.com/users/chrisduerr/subscriptions","organizations_url":"https://api.github.com/users/chrisduerr/orgs","repos_url":"https://api.github.com/users/chrisduerr/repos","events_url":"https://api.github.com/users/chrisduerr/events{/privacy}","received_events_url":"https://api.github.com/users/chrisduerr/received_events","type":"User","user_view_type":"public","site_admin":false},"event":"referenced","commit_id":"77127fbb41748eae264b1a7578a3bd7d0f94d5c5","commit_url":"https://api.github.com/repos/alacritty/alacritty/commits/77127fbb41748eae264b1a7578a3bd7d0f94d5c5","created_at":"2019-10-24T22:26:35Z","performed_via_github_app":null},{"url":"https://api.github.com/repos/alacritty/alacritty/issues/comments/563458671","html_url":"https://github.com/alacritty/alacritty/issues/2914#issuecomment-563458671","issue_url":"https://api.github.com/repos/alacritty/alacritty/issues/2914","id":563458671,"node_id":"MDEyOklzc3VlQ29tbWVudDU2MzQ1ODY3MQ==","user":{"login":"virtualdxs","id":11588204,"node_id":"MDQ6VXNlcjExNTg4MjA0","avatar_url":"https://avatars.githubusercontent.com/u/11588204?v=4","gravatar_id":"","url":"https://api.github.com/users/virtualdxs","html_url":"https://github.com/virtualdxs","followers_url":"https://api.github.com/users/virtualdxs/followers","following_url":"https://api.github.com/users/virtualdxs/following{/other_user}","gists_url":"https://api.github.com/users/virtualdxs/gists{/gist_id}","starred_url":"https://api.github.com/users/virtualdxs/starred{/owner}{/repo}","subscriptions_url":"https://api.github.com/users/virtualdxs/subscriptions","organizations_url":"https://api.github.com/users/virtualdxs/orgs","repos_url":"https://api.github.com/users/virtualdxs/repos","events_url":"https://api.github.com/users/virtualdxs/events{/privacy}","received_events_url":"https://api.github.com/users/virtualdxs/received_events","type":"User","user_view_type":"public","site_admin":false},"created_at":"2019-12-09T21:57:07Z","updated_at":"2019-12-09T21:57:07Z","body":"I'm still seeing (what I think is) this issue on 0.4.0. I cause a bell, it mostly finishes the animation, but there's still an overlay of red (bell color) until I type another key. The opaqueness varies from bell to bell.\r\n\r\nUsing Xorg version 1.20.6\r\n\r\nGPU:\r\n\r\n    08:00.0 VGA compatible controller: NVIDIA Corporation GK208B [GeForce GT 710] (rev a1)\r\n\r\nBell config:\r\n\r\n    visual_bell:\r\n      animation: Linear\r\n      duration: 200\r\n      color: '0xff0000'\r\n","author_association":"NONE","reactions":{"url":"https://api.github.com/repos/alacritty/alacritty/issues/comments/563458671/reactions","total_count":0,"+1":0,"-1":0,"laugh":0,"hooray":0,"confused":0,"heart":0,"rocket":0,"eyes":0},"performed_via_github_app":null,"event":"commented","actor":{"login":"virtualdxs","id":11588204,"node_id":"MDQ6VXNlcjExNTg4MjA0","avatar_url":"https://avatars.githubusercontent.com/u/11588204?v=4","gravatar_id":"","url":"https://api.github.com/users/virtualdxs","html_url":"https://github.com/virtualdxs","followers_url":"https://api.github.com/users/virtualdxs/followers","following_url":"https://api.github.com/users/virtualdxs/following{/other_user}","gists_url":"https://api.github.com/users/virtualdxs/gists{/gist_id}","starred_url":"https://api.github.com/users/virtualdxs/starred{/owner}{/repo}","subscriptions_url":"https://api.github.com/users/virtualdxs/subscriptions","organizations_url":"https://api.github.com/users/virtualdxs/orgs","repos_url":"https://api.github.com/users/virtualdxs/repos","events_url":"https://api.github.com/users/virtualdxs/events{/privacy}","received_events_url":"https://api.github.com/users/virtualdxs/received_events","type":"User","user_view_type":"public","site_admin":false}},{"url":"https://api.github.com/repos/alacritty/alacritty/issues/comments/563459008","html_url":"https://github.com/alacritty/alacritty/issues/2914#issuecomment-563459008","issue_url":"https://api.github.com/repos/alacritty/alacritty/issues/2914","id":563459008,"node_id":"MDEyOklzc3VlQ29tbWVudDU2MzQ1OTAwOA==","user":{"login":"virtualdxs","id":11588204,"node_id":"MDQ6VXNlcjExNTg4MjA0","avatar_url":"https://avatars.githubusercontent.com/u/11588204?v=4","gravatar_id":"","url":"https://api.github.com/users/virtualdxs","html_url":"https://github.com/virtualdxs","followers_url":"https://api.github.com/users/virtualdxs/followers","following_url":"https://api.github.com/users/virtualdxs/following{/other_user}","gists_url":"https://api.github.com/users/virtualdxs/gists{/gist_id}","starred_url":"https://api.github.com/users/virtualdxs/starred{/owner}{/repo}","subscriptions_url":"https://api.github.com/users/virtualdxs/subscriptions","organizations_url":"https://api.github.com/users/virtualdxs/orgs","repos_url":"https://api.github.com/users/virtualdxs/repos","events_url":"https://api.github.com/users/virtualdxs/events{/privacy}","received_events_url":"https://api.github.com/users/virtualdxs/received_events","type":"User","user_view_type":"public","site_admin":false},"created_at":"2019-12-09T21:58:00Z","updated_at":"2019-12-09T21:58:00Z","body":"Note: I'm able to reproduce this on one computer with the above information, but not my laptop.","author_association":"NONE","reactions":{"url":"https://api.github.com/repos/alacritty/alacritty/issues/comments/563459008/reactions","total_count":0,"+1":0,"-1":0,"laugh":0,"hooray":0,"confused":0,"heart":0,"rocket":0,"eyes":0},"performed_via_github_app":null,"event":"commented","actor":{"login":"virtualdxs","id":11588204,"node_id":"MDQ6VXNlcjExNTg4MjA0","avatar_url":"https://avatars.githubusercontent.com/u/11588204?v=4","gravatar_id":"","url":"https://api.github.com/users/virtualdxs","html_url":"https://github.com/virtualdxs","followers_url":"https://api.github.com/users/virtualdxs/followers","following_url":"https://api.github.com/users/virtualdxs/following{/other_user}","gists_url":"https://api.github.com/users/virtualdxs/gists{/gist_id}","starred_url":"https://api.github.com/users/virtualdxs/starred{/owner}{/repo}","subscriptions_url":"https://api.github.com/users/virtualdxs/subscriptions","organizations_url":"https://api.github.com/users/virtualdxs/orgs","repos_url":"https://api.github.com/users/virtualdxs/repos","events_url":"https://api.github.com/users/virtualdxs/events{/privacy}","received_events_url":"https://api.github.com/users/virtualdxs/received_events","type":"User","user_view_type":"public","site_admin":false}},{"url":"https://api.github.com/repos/alacritty/alacritty/issues/comments/563465053","html_url":"https://github.com/alacritty/alacritty/issues/2914#issuecomment-563465053","issue_url":"https://api.github.com/repos/alacritty/alacritty/issues/2914","id":563465053,"node_id":"MDEyOklzc3VlQ29tbWVudDU2MzQ2NTA1Mw==","user":{"login":"chrisduerr","id":8886672,"node_id":"MDQ6VXNlcjg4ODY2NzI=","avatar_url":"https://avatars.githubusercontent.com/u/8886672?v=4","gravatar_id":"","url":"https://api.github.com/users/chrisduerr","html_url":"https://github.com/chrisduerr","followers_url":"https://api.github.com/users/chrisduerr/followers","following_url":"https://api.github.com/users/chrisduerr/following{/other_user}","gists_url":"https://api.github.com/users/chrisduerr/gists{/gist_id}","starred_url":"https://api.github.com/users/chrisduerr/starred{/owner}{/repo}","subscriptions_url":"https://api.github.com/users/chrisduerr/subscriptions","organizations_url":"https://api.github.com/users/chrisduerr/orgs","repos_url":"https://api.github.com/users/chrisduerr/repos","events_url":"https://api.github.com/users/chrisduerr/events{/privacy}","received_events_url":"https://api.github.com/users/chrisduerr/received_events","type":"User","user_view_type":"public","site_admin":false},"created_at":"2019-12-09T22:15:14Z","updated_at":"2019-12-09T22:15:14Z","body":"@virtualdxs Would you mind opening a separate issue for this?","author_association":"MEMBER","reactions":{"url":"https://api.github.com/repos/alacritty/alacritty/issues/comments/563465053/reactions","total_count":0,"+1":0,"-1":0,"laugh":0,"hooray":0,"confused":0,"heart":0,"rocket":0,"eyes":0},"performed_via_github_app":null,"event":"commented","actor":{"login":"chrisduerr","id":8886672,"node_id":"MDQ6VXNlcjg4ODY2NzI=","avatar_url":"https://avatars.githubusercontent.com/u/8886672?v=4","gravatar_id":"","url":"https://api.github.com/users/chrisduerr","html_url":"https://github.com/chrisduerr","followers_url":"https://api.github.com/users/chrisduerr/followers","following_url":"https://api.github.com/users/chrisduerr/following{/other_user}","gists_url":"https://api.github.com/users/chrisduerr/gists{/gist_id}","starred_url":"https://api.github.com/users/chrisduerr/starred{/owner}{/repo}","subscriptions_url":"https://api.github.com/users/chrisduerr/subscriptions","organizations_url":"https://api.github.com/users/chrisduerr/orgs","repos_url":"https://api.github.com/users/chrisduerr/repos","events_url":"https://api.github.com/users/chrisduerr/events{/privacy}","received_events_url":"https://api.github.com/users/chrisduerr/received_events","type":"User","user_view_type":"public","site_admin":false}},{"id":2868083081,"node_id":"MDE0Ok1lbnRpb25lZEV2ZW50Mjg2ODA4MzA4MQ==","url":"https://api.github.com/repos/alacritty/alacritty/issues/events/2868083081","actor":{"login":"virtualdxs","id":11588204,"node_id":"MDQ6VXNlcjExNTg4MjA0","avatar_url":"https://avatars.githubusercontent.com/u/11588204?v=4","gravatar_id":"","url":"https://api.github.com/users/virtualdxs","html_url":"https://github.com/virtualdxs","followers_url":"https://api.github.com/users/virtualdxs/followers","following_url":"https://api.github.com/users/virtualdxs/following{/other_user}","gists_url":"https://api.github.com/users/virtualdxs/gists{/gist_id}","starred_url":"https://api.github.com/users/virtualdxs/starred{/owner}{/repo}","subscriptions_url":"https://api.github.com/users/virtualdxs/subscriptions","organizations_url":"https://api.github.com/users/virtualdxs/orgs","repos_url":"https://api.github.com/users/virtualdxs/repos","events_url":"https://api.github.com/users/virtualdxs/events{/privacy}","received_events_url":"https://api.github.com/users/virtualdxs/received_events","type":"User","user_view_type":"public","site_admin":false},"event":"mentioned","commit_id":null,"commit_url":null,"created_at":"2019-12-09T22:15:14Z","performed_via_github_app":null},{"id":2868083086,"node_id":"MDE1OlN1YnNjcmliZWRFdmVudDI4NjgwODMwODY=","url":"https://api.github.com/repos/alacritty/alacritty/issues/events/2868083086","actor":{"login":"virtualdxs","id":11588204,"node_id":"MDQ6VXNlcjExNTg4MjA0","avatar_url":"https://avatars.githubusercontent.com/u/11588204?v=4","gravatar_id":"","url":"https://api.github.com/users/virtualdxs","html_url":"https://github.com/virtualdxs","followers_url":"https://api.github.com/users/virtualdxs/followers","following_url":"https://api.github.com/users/virtualdxs/following{/other_user}","gists_url":"https://api.github.com/users/virtualdxs/gists{/gist_id}","starred_url":"https://api.github.com/users/virtualdxs/starred{/owner}{/repo}","subscriptions_url":"https://api.github.com/users/virtualdxs/subscriptions","organizations_url":"https://api.github.com/users/virtualdxs/orgs","repos_url":"https://api.github.com/users/virtualdxs/repos","events_url":"https://api.github.com/users/virtualdxs/events{/privacy}","received_events_url":"https://api.github.com/users/virtualdxs/received_events","type":"User","user_view_type":"public","site_admin":false},"event":"subscribed","commit_id":null,"commit_url":null,"created_at":"2019-12-09T22:15:14Z","performed_via_github_app":null},{"url":"https://api.github.com/repos/alacritty/alacritty/issues/comments/563465239","html_url":"https://github.com/alacritty/alacritty/issues/2914#issuecomment-563465239","issue_url":"https://api.github.com/repos/alacritty/alacritty/issues/2914","id":563465239,"node_id":"MDEyOklzc3VlQ29tbWVudDU2MzQ2NTIzOQ==","user":{"login":"virtualdxs","id":11588204,"node_id":"MDQ6VXNlcjExNTg4MjA0","avatar_url":"https://avatars.githubusercontent.com/u/11588204?v=4","gravatar_id":"","url":"https://api.github.com/users/virtualdxs","html_url":"https://github.com/virtualdxs","followers_url":"https://api.github.com/users/virtualdxs/followers","following_url":"https://api.github.com/users/virtualdxs/following{/other_user}","gists_url":"https://api.github.com/users/virtualdxs/gists{/gist_id}","starred_url":"https://api.github.com/users/virtualdxs/starred{/owner}{/repo}","subscriptions_url":"https://api.github.com/users/virtualdxs/subscriptions","organizations_url":"https://api.github.com/users/virtualdxs/orgs","repos_url":"https://api.github.com/users/virtualdxs/repos","events_url":"https://api.github.com/users/virtualdxs/events{/privacy}","received_events_url":"https://api.github.com/users/virtualdxs/received_events","type":"User","user_view_type":"public","site_admin":false},"created_at":"2019-12-09T22:15:48Z","updated_at":"2019-12-09T22:15:48Z","body":"Will do.","author_association":"NONE","reactions":{"url":"https://api.github.com/repos/alacritty/alacritty/issues/comments/563465239/reactions","total_count":0,"+1":0,"-1":0,"laugh":0,"hooray":0,"confused":0,"heart":0,"rocket":0,"eyes":0},"performed_via_github_app":null,"event":"commented","actor":{"login":"virtualdxs","id":11588204,"node_id":"MDQ6VXNlcjExNTg4MjA0","avatar_url":"https://avatars.githubusercontent.com/u/11588204?v=4","gravatar_id":"","url":"https://api.github.com/users/virtualdxs","html_url":"https://github.com/virtualdxs","followers_url":"https://api.github.com/users/virtualdxs/followers","following_url":"https://api.github.com/users/virtualdxs/following{/other_user}","gists_url":"https://api.github.com/users/virtualdxs/gists{/gist_id}","starred_url":"https://api.github.com/users/virtualdxs/starred{/owner}{/repo}","subscriptions_url":"https://api.github.com/users/virtualdxs/subscriptions","organizations_url":"https://api.github.com/users/virtualdxs/orgs","repos_url":"https://api.github.com/users/virtualdxs/repos","events_url":"https://api.github.com/users/virtualdxs/events{/privacy}","received_events_url":"https://api.github.com/users/virtualdxs/received_events","type":"User","user_view_type":"public","site_admin":false}},{"actor":{"login":"virtualdxs","id":11588204,"node_id":"MDQ6VXNlcjExNTg4MjA0","avatar_url":"https://avatars.githubusercontent.com/u/11588204?v=4","gravatar_id":"","url":"https://api.github.com/users/virtualdxs","html_url":"https://github.com/virtualdxs","followers_url":"https://api.github.com/users/virtualdxs/followers","following_url":"https://api.github.com/users/virtualdxs/following{/other_user}","gists_url":"https://api.github.com/users/virtualdxs/gists{/gist_id}","starred_url":"https://api.github.com/users/virtualdxs/starred{/owner}{/repo}","subscriptions_url":"https://api.github.com/users/virtualdxs/subscriptions","organizations_url":"https://api.github.com/users/virtualdxs/orgs","repos_url":"https://api.github.com/users/virtualdxs/repos","events_url":"https://api.github.com/users/virtualdxs/events{/privacy}","received_events_url":"https://api.github.com/users/virtualdxs/received_events","type":"User","user_view_type":"public","site_admin":false},"created_at":"2019-12-09T22:20:25Z","updated_at":"2019-12-09T22:20:25Z","source":{"type":"issue","issue":{"url":"https://api.github.com/repos/alacritty/alacritty/issues/3083","repository_url":"https://api.github.com/repos/alacritty/alacritty","labels_url":"https://api.github.com/repos/alacritty/alacritty/issues/3083/labels{/name}","comments_url":"https://api.github.com/repos/alacritty/alacritty/issues/3083/comments","events_url":"https://api.github.com/repos/alacritty/alacritty/issues/3083/events","html_url":"https://github.com/alacritty/alacritty/issues/3083","id":535372910,"node_id":"MDU6SXNzdWU1MzUzNzI5MTA=","number":3083,"title":"Visual bell persists past end of animation","user":{"login":"virtualdxs","id":11588204,"node_id":"MDQ6VXNlcjExNTg4MjA0","avatar_url":"https://avatars.githubusercontent.com/u/11588204?v=4","gravatar_id":"","url":"https://api.github.com/users/virtualdxs","html_url":"https://github.com/virtualdxs","followers_url":"https://api.github.com/users/virtualdxs/followers","following_url":"https://api.github.com/users/virtualdxs/following{/other_user}","gists_url":"https://api.github.com/users/virtualdxs/gists{/gist_id}","starred_url":"https://api.github.com/users/virtualdxs/starred{/owner}{/repo}","subscriptions_url":"https://api.github.com/users/virtualdxs/subscriptions","organizations_url":"https://api.github.com/users/virtualdxs/orgs","repos_url":"https://api.github.com/users/virtualdxs/repos","events_url":"https://api.github.com/users/virtualdxs/events{/privacy}","received_events_url":"https://api.github.com/users/virtualdxs/received_events","type":"User","user_view_type":"public","site_admin":false},"labels":[{"id":327960155,"node_id":"MDU6TGFiZWwzMjc5NjAxNTU=","url":"https://api.github.com/repos/alacritty/alacritty/labels/B%20-%20bug","name":"B - bug","color":"c6071e","default":false,"description":""},{"id":327960159,"node_id":"MDU6TGFiZWwzMjc5NjAxNTk=","url":"https://api.github.com/repos/alacritty/alacritty/labels/A%20-%20needs%20repro","name":"A - needs repro","color":"fef2c0","default":false,"description":null}],"state":"closed","locked":false,"assignee":null,"assignees":[],"milestone":null,"comments":26,"created_at":"2019-12-09T22:20:24Z","updated_at":"2020-10-31T13:14:47Z","closed_at":"2020-10-31T13:14:47Z","author_association":"NONE","type":null,"active_lock_reason":null,"sub_issues_summary":{"total":0,"completed":0,"percent_completed":0},"issue_dependencies_summary":{"blocked_by":0,"total_blocked_by":0,"blocking":0,"total_blocking":0},"repository":{"id":51980455,"node_id":"MDEwOlJlcG9zaXRvcnk1MTk4MDQ1NQ==","name":"alacritty","full_name":"alacritty/alacritty","private":false,"owner":{"login":"alacritty","id":29714349,"node_id":"MDEyOk9yZ2FuaXphdGlvbjI5NzE0MzQ5","avatar_url":"https://avatars.githubusercontent.com/u/29714349?v=4","gravatar_id":"","url":"https://api.github.com/users/alacritty","html_url":"https://github.com/alacritty","followers_url":"https://api.github.com/users/alacritty/followers","following_url":"https://api.github.com/users/alacritty/following{/other_user}","gists_url":"https://api.github.com/users/alacritty/gists{/gist_id}","starred_url":"https://api.github.com/users/alacritty/starred{/owner}{/repo}","subscriptions_url":"https://api.github.com/users/alacritty/subscriptions","organizations_url":"https://api.github.com/users/alacritty/orgs","repos_url":"https://api.github.com/users/alacritty/repos","events_url":"https://api.github.com/users/alacritty/events{/privacy}","received_events_url":"https://api.github.com/users/alacritty/received_events","type":"Organization","user_view_type":"public","site_admin":false},"html_url":"https://github.com/alacritty/alacritty","description":"A cross-platform, OpenGL terminal emulator.","fork":false,"url":"https://api.github.com/repos/alacritty/alacritty","forks_url":"https://api.github.com/repos/alacritty/alacritty/forks","keys_url":"https://api.github.com/repos/alacritty/alacritty/keys{/key_id}","collaborators_url":"https://api.github.com/repos/alacritty/alacritty/collaborators{/collaborator}","teams_url":"https://api.github.com/repos/alacritty/alacritty/teams","hooks_url":"https://api.github.com/repos/alacritty/alacritty/hooks","issue_events_url":"https://api.github.com/repos/alacritty/alacritty/issues/events{/number}","events_url":"https://api.github.com/repos/alacritty/alacritty/events","assignees_url":"https://api.github.com/repos/alacritty/alacritty/assignees{/user}","branches_url":"https://api.github.com/repos/alacritty/alacritty/branches{/branch}","tags_url":"https://api.github.com/repos/alacritty/alacritty/tags","blobs_url":"https://api.github.com/repos/alacritty/alacritty/git/blobs{/sha}","git_tags_url":"https://api.github.com/repos/alacritty/alacritty/git/tags{/sha}","git_refs_url":"https://api.github.com/repos/alacritty/alacritty/git/refs{/sha}","trees_url":"https://api.github.com/repos/alacritty/alacritty/git/trees{/sha}","statuses_url":"https://api.github.com/repos/alacritty/alacritty/statuses/{sha}","languages_url":"https://api.github.com/repos/alacritty/alacritty/languages","stargazers_url":"https://api.github.com/repos/alacritty/alacritty/stargazers","contributors_url":"https://api.github.com/repos/alacritty/alacritty/contributors","subscribers_url":"https://api.github.com/repos/alacritty/alacritty/subscribers","subscription_url":"https://api.github.com/repos/alacritty/alacritty/subscription","commits_url":"https://api.github.com/repos/alacritty/alacritty/commits{/sha}","git_commits_url":"https://api.github.com/repos/alacritty/alacritty/git/commits{/sha}","comments_url":"https://api.github.com/repos/alacritty/alacritty/comments{/number}","issue_comment_url":"https://api.github.com/repos/alacritty/alacritty/issues/comments{/number}","contents_url":"https://api.github.com/repos/alacritty/alacritty/contents/{+path}","compare_url":"https://api.github.com/repos/alacritty/alacritty/compare/{base}...{head}","merges_url":"https://api.github.com/repos/alacritty/alacritty/merges","archive_url":"https://api.github.com/repos/alacritty/alacritty/{archive_format}{/ref}","downloads_url":"https://api.github.com/repos/alacritty/alacritty/downloads","issues_url":"https://api.github.com/repos/alacritty/alacritty/issues{/number}","pulls_url":"https://api.github.com/repos/alacritty/alacritty/pulls{/number}","milestones_url":"https://api.github.com/repos/alacritty/alacritty/milestones{/number}","notifications_url":"https://api.github.com/repos/alacritty/alacritty/notifications{?since,all,participating}","labels_url":"https://api.github.com/repos/alacritty/alacritty/labels{/name}","releases_url":"https://api.github.com/repos/alacritty/alacritty/releases{/id}","deployments_url":"https://api.github.com/repos/alacritty/alacritty/deployments","created_at":"2016-02-18T05:02:30Z","updated_at":"2025-12-12T22:18:57Z","pushed_at":"2025-12-05T15:27:56Z","git_url":"git://github.com/alacritty/alacritty.git","ssh_url":"git@github.com:alacritty/alacritty.git","clone_url":"https://github.com/alacritty/alacritty.git","svn_url":"https://github.com/alacritty/alacritty","homepage":"https://alacritty.org","size":14099,"stargazers_count":61387,"watchers_count":61387,"language":"Rust","has_issues":true,"has_projects":false,"has_downloads":true,"has_wiki":true,"has_pages":false,"has_discussions":false,"forks_count":3243,"mirror_url":null,"archived":false,"disabled":false,"open_issues_count":331,"license":{"key":"apache-2.0","name":"Apache License 2.0","spdx_id":"Apache-2.0","url":"https://api.github.com/licenses/apache-2.0","node_id":"MDc6TGljZW5zZTI="},"allow_forking":true,"is_template":false,"web_commit_signoff_required":false,"topics":["bsd","gpu","linux","macos","opengl","rust","terminal","terminal-emulators","vte","windows"],"visibility":"public","forks":3243,"open_issues":331,"watchers":61387,"default_branch":"master","permissions":{"admin":false,"maintain":false,"push":false,"triage":false,"pull":true}},"body":"I'm still seeing what I thought was #2914 on 0.4.0. I cause a bell, it mostly finishes the animation, but there's still an overlay of red (bell color) until I type another key. The opaqueness varies from bell to bell.\r\n\r\nI'm able to reproduce on the below system but not my main laptop.\r\n### Bell configuration:\r\n\r\n    visual_bell:\r\n      animation: Linear\r\n      duration: 200\r\n      color: '0xff0000'\r\n\r\n### System\r\n\r\nOS: Arch Linux\r\nVersion: alacritty 0.4.0\r\nXorg version 1.20.6 and dwm\r\nGPU: \r\n\r\n    08:00.0 VGA compatible controller: NVIDIA Corporation GK208B [GeForce GT 710] (rev a1)","reactions":{"url":"https://api.github.com/repos/alacritty/alacritty/issues/3083/reactions","total_count":3,"+1":3,"-1":0,"laugh":0,"hooray":0,"confused":0,"heart":0,"rocket":0,"eyes":0},"timeline_url":"https://api.github.com/repos/alacritty/alacritty/issues/3083/timeline","performed_via_github_app":null,"state_reason":"completed"}},"event":"cross-referenced"},{"id":3249249070,"node_id":"MDE1OlJlZmVyZW5jZWRFdmVudDMyNDkyNDkwNzA=","url":"https://api.github.com/repos/alacritty/alacritty/issues/events/3249249070","actor":{"login":"roychoo","id":1853311,"node_id":"MDQ6VXNlcjE4NTMzMTE=","avatar_url":"https://avatars.githubusercontent.com/u/1853311?v=4","gravatar_id":"","url":"https://api.github.com/users/roychoo","html_url":"https://github.com/roychoo","followers_url":"https://api.github.com/users/roychoo/followers","following_url":"https://api.github.com/users/roychoo/following{/other_user}","gists_url":"https://api.github.com/users/roychoo/gists{/gist_id}","starred_url":"https://api.github.com/users/roychoo/starred{/owner}{/repo}","subscriptions_url":"https://api.github.com/users/roychoo/subscriptions","organizations_url":"https://api.github.com/users/roychoo/orgs","repos_url":"https://api.github.com/users/roychoo/repos","events_url":"https://api.github.com/users/roychoo/events{/privacy}","received_events_url":"https://api.github.com/users/roychoo/received_events","type":"User","user_view_type":"public","site_admin":false},"event":"referenced","commit_id":"f11c5bc86c72ff083b31630d4bb5e6ac16cce252","commit_url":"https://api.github.com/repos/roychoo/alacritty/commits/f11c5bc86c72ff083b31630d4bb5e6ac16cce252","created_at":"2020-04-19T16:47:54Z","performed_via_github_app":null}]