{"id":141,"status":"Fixed","summary":"\u0027\"--help\" is not a valid option\u0027","labels":["Type-Defect","Priority-Medium"],"stars":1,"commentCount":3,"comments":[{"id":0,"commenterId":-8565359677229908361,"content":"\u003cb\u003eWhat steps will reproduce the problem?\u003c/b\u003e\n1. java -jar compiler.jar --help\r\n\r\n\u003cb\u003eWhat is the expected output? What do you see instead?\u003c/b\u003e\nExpected help text. Help text about the flags are displayed, but initially \r\ncompiler claims: \u0027\u0026quot;--help\u0026quot; is not a valid option\u0027.\r\n\r\n\u003cb\u003eWhat version of the product are you using? On what operating system?\u003c/b\u003e\nClosure 20100330 release, Windows Vista.\r\n\r\n\u003cb\u003ePlease provide any additional information below.\u003c/b\u003e\nI also noticed the structure of the help text is also different from \r\nprevious releases(?). Also \u0026quot;--help\u0026quot; is not listed among the flags.\r\n\r\n// Fredrik","timestamp":1270653340,"attachments":[]},{"id":1,"commenterId":-5060162230523776870,"content":"","timestamp":1270667469,"attachments":[]},{"id":2,"commenterId":-7699928860083865744,"content":"This issue was closed by revision r175.","timestamp":1270750322,"attachments":[]}]}